rules/__init__.py
rules/compat.py
rules/decorators.py
rules/docs.py
rules/extras.py
rules/middleware.py
rules/mixins.py
rules/models.py
rules/perms.py
rules/settings.py
rules/signals.py
rules/urldecorators.py
rules/utils.py
rules/api/__init__.py
rules/api/keys.py
rules/api/rules.py
rules/api/serializers.py
rules/api/sessions.py
rules/static/js/djaodjin-resources-vue.js
rules/static/js/djaodjin-resources.js
rules/static/js/djaodjin-rules-angular.js
rules/static/js/djaodjin-rules-vue.js
rules/templates/rules/app_dashboard.html
rules/templates/rules/engagement.html
rules/templates/rules/forward_error.html
rules/urls/__init__.py
rules/urls/apply.py
rules/urls/configure.py
rules/urls/api/__init__.py
rules/urls/api/proxy.py
rules/views/__init__.py
rules/views/app.py
rules/views/download.py
djaodjin_rules-0.4.11.dist-info/METADATA
djaodjin_rules-0.4.11.dist-info/WHEEL
djaodjin_rules-0.4.11.dist-info/top_level.txt
djaodjin_rules-0.4.11.dist-info/RECORD
