Metadata-Version: 2.4
Name: djaodjin-rules
Version: 0.4.11
Summary: Flexible framework to check permissions to URIs and forward HTTP requests
Author-email: The DjaoDjin Team <help@djaodjin.com>
Maintainer-email: The DjaoDjin Team <help@djaodjin.com>
License: BSD-2-Clause
Project-URL: repository, https://github.com/djaodjin/djaodjin-rules
Project-URL: documentation, https://djaodjin-rules.readthedocs.io/
Project-URL: changelog, https://github.com/djaodjin/djaodjin-rules/changelog
Keywords: django,security,rules,proxy,rbac
Classifier: Framework :: Django
Classifier: Environment :: Web Environment
Classifier: Programming Language :: Python
Classifier: License :: OSI Approved :: BSD License
Requires-Python: >=3.7
Requires-Dist: Django>=1.11
Requires-Dist: djangorestframework>=3.9.4
Requires-Dist: djaodjin-deployutils>=0.14.0
Requires-Dist: requests>=2.22.0
Requires-Dist: python-dateutil>=2.8.0
